wqrfnium/__init__.py
wqrfnium/test.py
wqrfnium/test_api.py
wqrfnium/wqrfnium.py
wqrfnium/wqrfnium_api.py
wqrfnium-0.3.0.dist-info/LICENSE
wqrfnium-0.3.0.dist-info/METADATA
wqrfnium-0.3.0.dist-info/WHEEL
wqrfnium-0.3.0.dist-info/top_level.txt
wqrfnium-0.3.0.dist-info/RECORD
