Metadata-Version: 2.1
Name: wqrfnium
Version: 0.3.0
Summary: to fix the selenium error which caused by ui change,wqrfnium can find element!
Home-page: https://github.com/Woqurefan/wqrf_selenium
Author: wqrf
Author-email: 1074321997@qq.com
License: MIT
Keywords: wqrf
Platform: UNKNOWN
